odoo/addons/pos_order_copy/README.rst
odoo/addons/pos_order_copy/__init__.py
odoo/addons/pos_order_copy/__manifest__.py
odoo/addons/pos_order_copy/i18n/it.po
odoo/addons/pos_order_copy/i18n/pos_order_copy.pot
odoo/addons/pos_order_copy/models/__init__.py
odoo/addons/pos_order_copy/models/pos_order.py
odoo/addons/pos_order_copy/models/pos_session.py
odoo/addons/pos_order_copy/readme/CONTRIBUTORS.md
odoo/addons/pos_order_copy/readme/DESCRIPTION.md
odoo/addons/pos_order_copy/static/description/icon.png
odoo/addons/pos_order_copy/static/description/index.html
odoo/addons/pos_order_copy/static/src/app/product_screen/CopyOrderButton.esm.js
odoo/addons/pos_order_copy/static/src/app/product_screen/CopyOrderButton.xml
odoo/addons/pos_order_copy/static/src/app/store/pos_store.esm.js
odoo/addons/pos_order_copy/static/src/app/ticket_screen/ticket_screen.esm.js
odoo/addons/pos_order_copy/static/src/app/ticket_screen/ticket_screen.xml
odoo_addon_pos_order_copy-17.0.1.0.0.4.dist-info/METADATA
odoo_addon_pos_order_copy-17.0.1.0.0.4.dist-info/WHEEL
odoo_addon_pos_order_copy-17.0.1.0.0.4.dist-info/top_level.txt
odoo_addon_pos_order_copy-17.0.1.0.0.4.dist-info/RECORD
